{
  "backdrop_path": "https://image.tmdb.org/t/p/w500/1qSo3zT9XAQYcbZaLBn46mTeTHZ.jpg",
  "id": 569547,
  "title": "Black Mirror: Bandersnatch",
  "poster_path": "https://image.tmdb.org/t/p/w500/fR0VZ0VE598zl1lrYf7IfBqEwQ2.jpg",
  "release_date": "2018-12-28",
  "vote_average": 6.769,
  "vote_count": 3730,
  "popularity": 24.185,
  "overview": "In 1984, a young programmer begins to question reality as he adapts a dark fantasy novel into a video game. A mind-bending tale with multiple endings.",
  "imdb_id": "tt9495224",
  "budget": 0,
  "homepage": "http://www.netflix.com/title/80988062",
  "revenue": 0,
  "runtime": 90,
  "tagline": "",
  "genres": [
    "Science Fiction",
    "Mystery",
    "Drama",
    "Thriller",
    "TV Movie"
  ],
  "production_companies": [
    "House of Tomorrow"
  ],
  "production_countries": [
    "US",
    "GB"
  ],
  "credits": {
    "cast": [
      {
        "name": "Fionn Whitehead",
        "character": "Stefan Butler",
        "profile_path": "https://image.tmdb.org/t/p/w185/gnZoQVp29ozHoMU8HysueZtmXs8.jpg"
      },
      {
        "name": "Craig Parkinson",
        "character": "Peter Butler",
        "profile_path": "https://image.tmdb.org/t/p/w185/pVv5G6s2WqtuQf2sdRLHdUuREAp.jpg"
      },
      {
        "name": "Alice Lowe",
        "character": "Dr. Haynes",
        "profile_path": "https://image.tmdb.org/t/p/w185/xdsdqVc8yDdHd677a0rzQRwQZ5G.jpg"
      },
      {
        "name": "Asim Chaudhry",
        "character": "Mohan Thakur",
        "profile_path": "https://image.tmdb.org/t/p/w185/1F0DwOpxUAEpw5iovMHZ5Y1C8n6.jpg"
      },
      {
        "name": "Will Poulter",
        "character": "Colin Ritman",
        "profile_path": "https://image.tmdb.org/t/p/w185/9blYMaj79VGC6BHTLmJp3V5S8r3.jpg"
      },
      {
        "name": "Tallulah Haddon",
        "character": "Kitty",
        "profile_path": "https://image.tmdb.org/t/p/w185/hjr2yU4mFCWlZZ9XUOQZkXkuMU4.jpg"
      },
      {
        "name": "Catriona Knox",
        "character": "Leslie",
        "profile_path": "https://image.tmdb.org/t/p/w185/wIOYVjWCdC9iOHNAkQQXdRyokRM.jpg"
      },
      {
        "name": "Paul Bradley",
        "character": "Robin",
        "profile_path": ""
      },
      {
        "name": "Jonathan Aris",
        "character": "Crispin",
        "profile_path": "https://image.tmdb.org/t/p/w185/46T3x7CePc22Z5KvkR4OulmVORU.jpg"
      },
      {
        "name": "A.J. Houghton",
        "character": "Young Stefan",
        "profile_path": ""
      },
      {
        "name": "Fleur Keith",
        "character": "Mum",
        "profile_path": "https://image.tmdb.org/t/p/w185/3l86j2NCJfiTia7qwtfsltCa3i2.jpg"
      },
      {
        "name": "Laura Evelyn",
        "character": "Pearl Ritman",
        "profile_path": "https://image.tmdb.org/t/p/w185/pOAhLsr4ZFSjxsiADRFBTtruO0z.jpg"
      },
      {
        "name": "Alan Asaad",
        "character": "Satpal",
        "profile_path": "https://image.tmdb.org/t/p/w185/9M6wGNkiX4pUkqHvs9Yu52VHQFa.jpg"
      },
      {
        "name": "Suzanne Burden",
        "character": "Judith Mulligan",
        "profile_path": "https://image.tmdb.org/t/p/w185/Qt2uuEDQWLSVlBrhjNYew9lWZQ.jpg"
      },
      {
        "name": "Jeff Minter",
        "character": "Jerome F. Davies",
        "profile_path": ""
      },
      {
        "name": "Sandra Teles",
        "character": "Reporter",
        "profile_path": "https://image.tmdb.org/t/p/w185/hW911uY5D0HYxe8utGvwsISEovm.jpg"
      },
      {
        "name": "Rochenda Sandall",
        "character": "Pippa 1st AD",
        "profile_path": "https://image.tmdb.org/t/p/w185/gWdYgLh5yx1KlTHSjRZONoGAqKi.jpg"
      },
      {
        "name": "Ellie Piercy",
        "character": "Receptionist",
        "profile_path": "https://image.tmdb.org/t/p/w185/xASISRQYOoIhfqDOeouwNe5HyIc.jpg"
      },
      {
        "name": "Tom McCall",
        "character": "Paramedic",
        "profile_path": "https://image.tmdb.org/t/p/w185/vGJtpTTepzZoc2aO8XJuUzZH49r.jpg"
      },
      {
        "name": "Jon-Jo Inkpen",
        "character": "Pax",
        "profile_path": "https://image.tmdb.org/t/p/w185/5amr19elGDOghUjkYWypRROO2U4.jpg"
      },
      {
        "name": "Stephen Rashbrook",
        "character": "Narrator",
        "profile_path": "https://image.tmdb.org/t/p/w185/6kPecykES1JKmYBtXl9wKGqhCMj.jpg"
      }
    ],
    "crew": [
      {
        "name": "David Slade",
        "department": "Directing",
        "job": "Director",
        "profile_path": "https://image.tmdb.org/t/p/w185/9jL9OasecqvhQFvGYQtB4K6omGf.jpg"
      }
    ]
  },
  "keywords": [
    "video game",
    "technology",
    "choice",
    "free will",
    "british noir",
    "tech noir",
    "programmer",
    "interactive",
    "choose your own adventure",
    "video game development"
  ],
  "mpaa": "R",
  "summaries": [
    "A young programmer starts to question reality when he adapts a mad writer's fantasy novel into a video game.",
    "In 1984. Stefan is developing a computer game based on the book 'Bandersnatch', a novel where you get to make choices that determine the story. He has an opportunity to take his game to Tuckersoft, a software company, and have them release it. However, the more he works on the game the more his life emulates the game, with choices being made that are out of his control. Stefan appears to be going insane.—."
  ],
  "synopsis": "",
  "imdb_score": 7.1
}